{
    "0": {
        "name": "6 x 5",
        "timeout": 0,
        "runtime": "60.505",
        "query_prob": "0.87630"
    },
    "1": {
        "name": "6 x 6",
        "timeout": 0,
        "runtime": "72.486",
        "query_prob": "0.88160"
    },
    "2": {
        "name": "7 x 4",
        "timeout": 0,
        "runtime": "133.340",
        "query_prob": "0.86821"
    },
    "3": {
        "name": "7 x 5",
        "timeout": 0,
        "runtime": "78.965",
        "query_prob": "0.88057"
    },
    "4": {
        "name": "7 x 6",
        "timeout": 0,
        "runtime": "62.740",
        "query_prob": "0.88541"
    },
    "5": {
        "name": "7 x 7",
        "timeout": 0,
        "runtime": "39.413",
        "query_prob": "0.88960"
    },
    "6": {
        "name": "8 x 4",
        "timeout": 0,
        "runtime": "108.750",
        "query_prob": "0.86994"
    },
    "7": {
        "name": "8 x 5",
        "timeout": 0,
        "runtime": "136.208",
        "query_prob": "0.88120"
    },
    "8": {
        "name": "8 x 6",
        "timeout": 0,
        "runtime": "40.683",
        "query_prob": "0.88957"
    },
    "9": {
        "name": "8 x 7",
        "timeout": 0,
        "runtime": "69.391",
        "query_prob": "0.88998"
    },
    "10": {
        "name": "8 x 8",
        "timeout": 0,
        "runtime": "122.314",
        "query_prob": "0.89058"
    },
    "11": {
        "name": "9 x 3",
        "timeout": 0,
        "runtime": "118.719",
        "query_prob": "0.81405"
    },
    "12": {
        "name": "9 x 4",
        "timeout": 0,
        "runtime": "114.333",
        "query_prob": "0.86908"
    },
    "13": {
        "name": "9 x 5",
        "timeout": 0,
        "runtime": "36.105",
        "query_prob": "0.88916"
    },
    "14": {
        "name": "9 x 6",
        "timeout": 0,
        "runtime": "79.440",
        "query_prob": "0.88985"
    },
    "15": {
        "name": "9 x 7",
        "timeout": 0,
        "runtime": "129.323",
        "query_prob": "0.89050"
    },
    "16": {
        "name": "9 x 8",
        "timeout": 0,
        "runtime": "34.700",
        "query_prob": "0.89711"
    },
    "17": {
        "name": "9 x 9",
        "timeout": 0,
        "runtime": "59.624",
        "query_prob": "0.89692"
    }
}
